fusefs/__init__.py
fusefs/cli.py
fusefs/fusefs.py
fusefs-0.0.2.dist-info/AUTHORS.rst
fusefs-0.0.2.dist-info/LICENSE
fusefs-0.0.2.dist-info/LICENSE.md
fusefs-0.0.2.dist-info/METADATA
fusefs-0.0.2.dist-info/WHEEL
fusefs-0.0.2.dist-info/entry_points.txt
fusefs-0.0.2.dist-info/top_level.txt
fusefs-0.0.2.dist-info/RECORD
