Metadata-Version: 2.1
Name: fusefs
Version: 0.0.2
Summary: FuseFS: FUSE <-> pyFilesystem adapter
Home-page: https://gitlab.com/skeledrew/fusefs
Author: Andrew Phillips
Author-email: skeledrew@gmail.com
License: UNKNOWN
Keywords: fusefs
Platform: UNKNOWN
Classifier: Development Status :: 2 - Pre-Alpha
Classifier: Intended Audience :: Developers
Classifier: Natural Language :: English
Classifier: Programming Language :: Python :: 3
Classifier: Programming Language :: Python :: 3.6
Classifier: Programming Language :: Python :: 3.7
Requires-Dist: Click (>=6.0)
Requires-Dist: fs (>=2.4.11)
Requires-Dist: fusepy (>=3.0.1)
